[ 
  {"pk": 1,
	 "model": "ingredients.Unit",
	 "fields":
		{"name": "kilogram",
		 "short_name": "kg"
		}
	},
    
  {"pk": 2,
	 "model": "ingredients.Unit",
	 "fields":
		{"name": "gram",
		 "short_name": "g"
		}
	},
    
  {"pk": 3,
	 "model": "ingredients.Unit",
	 "fields":
		{"name": "aantal",
		 "short_name": ""
		}
	},
    
  {"pk": 4,
	 "model": "ingredients.Unit",
	 "fields":
		{"name": "deciliter",
		 "short_name": "dl"
		}
	},
    
  {"pk": 5,
	 "model": "ingredients.Unit",
	 "fields":
		{"name": "snuifje",
		"short_name": "snuifje"
		}
	},
	
	
	
	
	
	
	{"pk": 1,
	 "model": "ingredients.Country",
	 "fields":
		{"name": "Country1",
		 "distance": 0.0
		}
	},

	{"pk": 2,
	 "model": "ingredients.Country",
	 "fields":
		{"name": "Country2",
		 "distance": 1000.0
		}
	},
	
	
	
	
	
	

	{"pk": 1,
	 "model": "ingredients.TransportMethod",
	 "fields":
		{"name": "Car",
		 "emission_per_km": 5
		}
	},

	{"pk": 2,
	 "model": "ingredients.TransportMethod",
	 "fields":
		{"name": "Boat",
		 "emission_per_km": 1
		}
	},

	
	
  
	
	
	
  {"pk": 1,
  "model": "ingredients.Ingredient",
  "fields":
  	{"name": "Aardappel",
  	"plural_name": "Aardappellen",
  	"type": 1,
  	"category": 2,
  	"veganism": 2,
  	"description": "Een stoeme patat",
  	"conservation_tip": "Steek ze onder de grond",
  	"properties": "Rijk aan vitamine C",
  	"source": "Vanalles",
  	"base_footprint": 0.5,
  	"accepted": true}},
  
  {"pk": 1,
  "model": "ingredients.VegetalIngredient",
  "fields":
  	{"ingredient": 1,
  	"preservability": 5,
  	"preservation_footprint": 0}},
  
  {"pk": 2,
  "model": "ingredients.Synonym",
  "fields":
    {"name": "Patat",
    "plural_name": "Patatten",
    "ingredient": 1}},

  {"pk": 1,
  "model": "ingredients.CanUseUnit",
  "fields": 
  	{"ingredient": 1,
  	"unit": 1,
  	"conversion_factor": 1}},

  {"pk": 1,
  "model": "ingredients.AvailableInCountry",
  "fields":
  	{"ingredient": 1,
  	"location": 2,
  	"transport_method": 1,
  	"production_type": "Broeikas",
  	"extra_production_footprint": 0.5,
  	"date_from": "2000-01-01",
  	"date_until": "2000-12-31",
  	"footprint": 0.5}},
  	
  	
  	
  	
  {"pk": 2,
  "model": "ingredients.Ingredient",
  "fields":
  	{"name": "Ei",
    "plural_name": "Eieren",
  	"type": 0,
  	"category": 10,
  	"veganism": 1,
  	"description": "Een ei",
  	"conservation_tip": "Steek ze onder de grond",
  	"properties": "Rijk aan vitamine C",
  	"source": "Vanalles",
  	"base_footprint": 0.5,
  	"accepted": true}},

  {"pk": 2,
  "model": "ingredients.CanUseUnit",
  "fields": 
  	{"ingredient": 2,
  	"unit": 3,
  	"conversion_factor": 1}}
 
]